Metadata-Version: 2.1
Name: torchbearer
Version: 0.5.5
Summary: A model training library for pytorch
Home-page: https://github.com/pytorchbearer/torchbearer
Download-URL: https://github.com/pytorchbearer/torchbearer/archive/0.5.5.tar.gz
Author: Matt Painter
Author-email: mp2u16@ecs.soton.ac.uk
Classifier: License :: OSI Approved :: MIT License
Requires-Python: >=2.7,!=3.0.*,!=3.1.*,!=3.2.*,!=3.3.*,!=3.4.*
License-File: LICENSE
Requires-Dist: torch >=1.0.0
Requires-Dist: numpy
Requires-Dist: tqdm
